intuiting_machine/__init__.py
intuiting_machine/githf.py
intuiting_machine-0.0.1.dist-info/LICENSE
intuiting_machine-0.0.1.dist-info/METADATA
intuiting_machine-0.0.1.dist-info/WHEEL
intuiting_machine-0.0.1.dist-info/top_level.txt
intuiting_machine-0.0.1.dist-info/RECORD
